odoo/addons/edi_project_oca/README.rst
odoo/addons/edi_project_oca/__init__.py
odoo/addons/edi_project_oca/__manifest__.py
odoo/addons/edi_project_oca/i18n/edi_project_oca.pot
odoo/addons/edi_project_oca/i18n/it.po
odoo/addons/edi_project_oca/models/__init__.py
odoo/addons/edi_project_oca/models/project_project.py
odoo/addons/edi_project_oca/models/project_task.py
odoo/addons/edi_project_oca/readme/CONTRIBUTORS.md
odoo/addons/edi_project_oca/readme/DESCRIPTION.md
odoo/addons/edi_project_oca/static/description/icon.png
odoo/addons/edi_project_oca/static/description/index.html
odoo/addons/edi_project_oca/views/edi_exchange_record.xml
odoo/addons/edi_project_oca/views/project_project.xml
odoo/addons/edi_project_oca/views/project_task.xml
odoo_addon_edi_project_oca-17.0.1.0.0.10.dist-info/METADATA
odoo_addon_edi_project_oca-17.0.1.0.0.10.dist-info/WHEEL
odoo_addon_edi_project_oca-17.0.1.0.0.10.dist-info/top_level.txt
odoo_addon_edi_project_oca-17.0.1.0.0.10.dist-info/RECORD
