Metadata-Version: 2.1
Name: odoo-addon-edi_project_oca
Version: 17.0.1.0.0.10
Requires-Python: >=3.10
Requires-Dist: odoo-addon-component_event>=17.0dev,<17.1dev
Requires-Dist: odoo-addon-edi_oca>=17.0dev,<17.1dev
Requires-Dist: odoo>=17.0a,<17.1dev
Summary: Define EDI Configuration for Projects and Tasks
Home-page: https://github.com/OCA/edi-framework
License: LGPL-3
Author: Camptocamp,Odoo Community Association (OCA)
Author-email: support@odoo-community.org
Classifier: Programming Language :: Python
Classifier: Framework :: Odoo
Classifier: Framework :: Odoo :: 17.0
Classifier: License :: OSI Approved :: GNU Lesser General Public License v3 (LGPLv3)
Classifier: Development Status :: 4 - Beta
